CHANGES
LICENSE
MANIFEST.in
README
setup.py
stepford.py
tests.py
stepford.egg-info/PKG-INFO
stepford.egg-info/SOURCES.txt
stepford.egg-info/dependency_links.txt
stepford.egg-info/top_level.txt