Metadata-Version: 1.1
Name: stepford
Version: 0.1
Summary: An implementation of the Facebook test user API
Home-page: https://github.com/demianbrecht/stepford
Author: Demian Brecht
Author-email: demianbrecht@gmail.com
License: UNKNOWN
Keywords: python,facebook,integration test,test users
Platform: UNKNOWN
Classifier: Development Status :: 4 - Beta
Classifier: Intended Audience :: Developers
Classifier: License :: OSI Approved :: BSD License
Classifier: Operating System :: OS Independent
Classifier: Programming Language :: Python :: 2.7
Classifier: Programming Language :: Python :: Implementation :: CPython
Classifier: Topic :: Software Development :: Libraries :: Python Modules
Classifier: Topic :: Software Development :: Quality Assurance
Classifier: Topic :: Software Development :: Testing
Classifier: Topic :: Utilities
